[
    {
        "名称": "光伏ETF",
        "YC": -13.34
    },
    {
        "名称": "煤炭ETF",
        "YC": -12.18
    },
    {
        "名称": "酒ETF",
        "YC": -7.47
    },
    {
        "名称": "券商ETF",
        "YC": -7.05
    },
    {
        "名称": "房地产ETF",
        "YC": -6.91
    },
    {
        "名称": "电子ETF",
        "YC": -6.17
    },
    {
        "名称": "科创创业ETF",
        "YC": -5.49
    },
    {
        "名称": "标普500ETF",
        "YC": -5.37
    },
    {
        "名称": "创业板50ETF",
        "YC": -5.1
    },
    {
        "名称": "央企创新驱动ETF",
        "YC": -4.85
    },
    {
        "名称": "通信ETF",
        "YC": -4.18
    },
    {
        "名称": "纳指ETF",
        "YC": -3.19
    },
    {
        "名称": "央企红利ETF基金",
        "YC": -3.11
    },
    {
        "名称": "创业板ETF",
        "YC": -3.04
    },
    {
        "名称": "纳指生物科技ETF",
        "YC": -2.16
    },
    {
        "名称": "电力ETF",
        "YC": -2.0
    },
    {
        "名称": "科创50ETF",
        "YC": -1.34
    },
    {
        "名称": "芯片ETF",
        "YC": -1.16
    },
    {
        "名称": "化工ETF",
        "YC": -1.15
    },
    {
        "名称": "中证红利ETF",
        "YC": -0.69
    },
    {
        "名称": "交通运输ETF",
        "YC": -0.5
    },
    {
        "名称": "沪深300ETF",
        "YC": -0.45
    },
    {
        "名称": "中药50ETF",
        "YC": -0.3
    },
    {
        "名称": "半导体ETF",
        "YC": -0.3
    },
    {
        "名称": "800ETF",
        "YC": 0.1
    },
    {
        "名称": "疫苗ETF",
        "YC": 0.17
    },
    {
        "名称": "军工ETF",
        "YC": 0.67
    },
    {
        "名称": "消费ETF",
        "YC": 0.73
    },
    {
        "名称": "上证50ETF",
        "YC": 0.88
    },
    {
        "名称": "日经ETF",
        "YC": 1.03
    },
    {
        "名称": "医疗器械ETF",
        "YC": 1.03
    },
    {
        "名称": "30年国债ETF",
        "YC": 1.24
    },
    {
        "名称": "人工智能AIETF",
        "YC": 1.29
    },
    {
        "名称": "中证500ETF华夏",
        "YC": 1.62
    },
    {
        "名称": "软件ETF",
        "YC": 1.66
    },
    {
        "名称": "智能汽车ETF",
        "YC": 1.71
    },
    {
        "名称": "医疗ETF",
        "YC": 2.14
    },
    {
        "名称": "云计算ETF",
        "YC": 2.45
    },
    {
        "名称": "新能源车龙头ETF",
        "YC": 2.71
    },
    {
        "名称": "资源ETF",
        "YC": 2.8
    },
    {
        "名称": "钢铁ETF",
        "YC": 3.4
    },
    {
        "名称": "上证综指ETF",
        "YC": 3.42
    },
    {
        "名称": "上证指数ETF",
        "YC": 3.55
    },
    {
        "名称": "红利低波ETF",
        "YC": 4.36
    },
    {
        "名称": "医药ETF",
        "YC": 4.71
    },
    {
        "名称": "金融ETF",
        "YC": 6.43
    },
    {
        "名称": "机器人ETF",
        "YC": 7.07
    },
    {
        "名称": "传媒ETF",
        "YC": 7.49
    },
    {
        "名称": "港股红利ETF",
        "YC": 7.82
    },
    {
        "名称": "日本东证指数ETF",
        "YC": 7.83
    },
    {
        "名称": "生物疫苗ETF",
        "YC": 9.21
    },
    {
        "名称": "畜牧养殖ETF",
        "YC": 9.34
    },
    {
        "名称": "农业ETF",
        "YC": 9.76
    },
    {
        "名称": "工业母机ETF",
        "YC": 10.88
    },
    {
        "名称": "银行ETF",
        "YC": 11.58
    },
    {
        "名称": "有色50ETF",
        "YC": 11.96
    },
    {
        "名称": "游戏ETF",
        "YC": 18.96
    },
    {
        "名称": "H股ETF",
        "YC": 20.53
    },
    {
        "名称": "恒生互联网ETF",
        "YC": 20.62
    },
    {
        "名称": "黄金ETF",
        "YC": 25.3
    },
    {
        "名称": "恒生医疗ETF",
        "YC": 47.18
    },
    {
        "名称": "港股创新药ETF",
        "YC": 61.1
    }
]