[
    {
        "l2name": "股份制银行II",
        "PotScore": -8.66,
        "主力净流入-净占比": 116.3
    },
    {
        "l2name": "国有大型银行II",
        "PotScore": -3.91,
        "主力净流入-净占比": 99.41
    },
    {
        "l2name": "保险II",
        "PotScore": -5.44,
        "主力净流入-净占比": 37.22
    },
    {
        "l2name": "农商行II",
        "PotScore": -10.83,
        "主力净流入-净占比": 26.66
    },
    {
        "l2name": "城商行II",
        "PotScore": -14.72,
        "主力净流入-净占比": 18.19
    },
    {
        "l2name": "电视广播II",
        "PotScore": -6.63,
        "主力净流入-净占比": 11.12000000000001
    },
    {
        "l2name": "医疗美容II",
        "PotScore": -3.45,
        "主力净流入-净占比": 8.2
    },
    {
        "l2name": "其他家电II",
        "PotScore": 4.32,
        "主力净流入-净占比": 5.99
    },
    {
        "l2name": "黄金II",
        "PotScore": -3.76,
        "主力净流入-净占比": -1.379999999999997
    },
    {
        "l2name": "旅游零售II",
        "PotScore": -1.8,
        "主力净流入-净占比": -16.37
    }
]