[
    {
        "l2name": "黄金II",
        "PotScore": 19.3,
        "主力净流入-净占比": 94.3
    },
    {
        "l2name": "油气开采II",
        "PotScore": -3.16,
        "主力净流入-净占比": 11.79
    },
    {
        "l2name": "冶钢原料II",
        "PotScore": 9.52,
        "主力净流入-净占比": -9.850000000000009
    },
    {
        "l2name": "农业综合II",
        "PotScore": -2.77,
        "主力净流入-净占比": -15.09
    },
    {
        "l2name": "国有大型银行II",
        "PotScore": -8.09,
        "主力净流入-净占比": -21.71
    },
    {
        "l2name": "城商行II",
        "PotScore": -14.32,
        "主力净流入-净占比": -22.08999999999999
    },
    {
        "l2name": "装修装饰II",
        "PotScore": -0.65,
        "主力净流入-净占比": -30.14000000000001
    },
    {
        "l2name": "地面兵装II",
        "PotScore": 1.32,
        "主力净流入-净占比": -31.75
    },
    {
        "l2name": "体育II",
        "PotScore": -3.29,
        "主力净流入-净占比": -37.08
    },
    {
        "l2name": "农商行II",
        "PotScore": -10.12,
        "主力净流入-净占比": -38.70999999999999
    }
]