[
    {
        "基金简称": "医疗ETF",
        "份额增长%": 4465.67
    },
    {
        "基金简称": "医疗器械ETF",
        "份额增长%": 1739.68
    },
    {
        "基金简称": "医药ETF",
        "份额增长%": 1795.66
    },
    {
        "基金简称": "恒生互联",
        "份额增长%": 533.68
    },
    {
        "基金简称": "酒ETF",
        "份额增长%": 707.24
    },
    {
        "基金简称": "光伏ETF",
        "份额增长%": 67.83
    },
    {
        "基金简称": "科创创业ETF",
        "份额增长%": 226.87
    },
    {
        "基金简称": "恒生医疗",
        "份额增长%": 7281.76
    },
    {
        "基金简称": "疫苗ETF",
        "份额增长%": -62.55
    },
    {
        "基金简称": "消费ETF",
        "份额增长%": 847.87
    },
    {
        "基金简称": "新能源车龙头ETF",
        "份额增长%": 85.74
    },
    {
        "基金简称": "化工ETF",
        "份额增长%": -33.25
    },
    {
        "基金简称": "农业ETF",
        "份额增长%": 126.1
    },
    {
        "基金简称": "畜牧养殖",
        "份额增长%": 692.94
    },
    {
        "基金简称": "生物疫苗",
        "份额增长%": -76.58
    },
    {
        "基金简称": "创业板ETF",
        "份额增长%": 644.0
    },
    {
        "基金简称": "科创50",
        "份额增长%": 840.41
    },
    {
        "基金简称": "创业板50ETF",
        "份额增长%": 207.38
    },
    {
        "基金简称": "300ETF",
        "份额增长%": 951.63
    },
    {
        "基金简称": "军工ETF",
        "份额增长%": 66.79
    },
    {
        "基金简称": "煤炭ETF",
        "份额增长%": 727.87
    },
    {
        "基金简称": "50ETF",
        "份额增长%": 272.71
    },
    {
        "基金简称": "机器人ETF",
        "份额增长%": 3179.5
    },
    {
        "基金简称": "电子ETF",
        "份额增长%": -78.31
    },
    {
        "基金简称": "软件ETF",
        "份额增长%": 242.33
    },
    {
        "基金简称": "800ETF",
        "份额增长%": 129.19
    },
    {
        "基金简称": "智能汽车",
        "份额增长%": 93.35
    },
    {
        "基金简称": "券商ETF",
        "份额增长%": 12.05
    },
    {
        "基金简称": "芯片ETF",
        "份额增长%": -18.25
    },
    {
        "基金简称": "半导体",
        "份额增长%": 130.15
    },
    {
        "基金简称": "传媒ETF",
        "份额增长%": 4.18
    },
    {
        "基金简称": "有色50ETF",
        "份额增长%": -72.8
    },
    {
        "基金简称": "综指ETF",
        "份额增长%": 654.84
    },
    {
        "基金简称": "中证500",
        "份额增长%": 156.51
    },
    {
        "基金简称": "中药",
        "份额增长%": -84.33
    },
    {
        "基金简称": "交通运输ETF",
        "份额增长%": -85.75
    },
    {
        "基金简称": "H股ETF",
        "份额增长%": -5.06
    },
    {
        "基金简称": "AI智能",
        "份额增长%": 274.36
    },
    {
        "基金简称": "钢铁ETF",
        "份额增长%": 490.18
    },
    {
        "基金简称": "央企分红",
        "份额增长%": -80.5
    },
    {
        "基金简称": "上证ETF",
        "份额增长%": 140.67
    },
    {
        "基金简称": "工业母机ETF",
        "份额增长%": -37.09
    },
    {
        "基金简称": "纳指生物",
        "份额增长%": 466.77
    },
    {
        "基金简称": "港股红利ETF",
        "份额增长%": 944.65
    },
    {
        "基金简称": "电力ETF",
        "份额增长%": 135.9
    },
    {
        "基金简称": "云计算",
        "份额增长%": 687.44
    },
    {
        "基金简称": "游戏ETF",
        "份额增长%": 167.66
    },
    {
        "基金简称": "HK创新药",
        "份额增长%": 5487.93
    },
    {
        "基金简称": "日经ETF",
        "份额增长%": 1248.15
    },
    {
        "基金简称": "金融ETF",
        "份额增长%": -16.84
    },
    {
        "基金简称": "30年国债",
        "份额增长%": 8063.23
    },
    {
        "基金简称": "东证ETF",
        "份额增长%": 875.32
    },
    {
        "基金简称": "通信ETF",
        "份额增长%": -26.17
    },
    {
        "基金简称": "央创ETF",
        "份额增长%": -50.54
    },
    {
        "基金简称": "中证红利",
        "份额增长%": 1048.02
    },
    {
        "基金简称": "银行ETF",
        "份额增长%": -24.55
    },
    {
        "基金简称": "资源ETF",
        "份额增长%": -43.35
    },
    {
        "基金简称": "地产ETF",
        "份额增长%": 96.8
    },
    {
        "基金简称": "标普500",
        "份额增长%": 324.52
    },
    {
        "基金简称": "纳指ETF",
        "份额增长%": 408.28
    },
    {
        "基金简称": "红利低波",
        "份额增长%": 13165.7
    },
    {
        "基金简称": "黄金ETF",
        "份额增长%": 203.61
    }
]