[
    {
        "代码": 603278,
        "l2name": "通用机械II",
        "名称": "大业股份",
        "总净流入占比_5日总和": 117.85,
        "PotScore": 1.27,
        "收盘价": 10.91,
        "涨跌幅": -7.23
    },
    {
        "代码": 600592,
        "l2name": "通用机械II",
        "名称": "龙溪股份",
        "总净流入占比_5日总和": 75.92,
        "PotScore": 1.03,
        "收盘价": 27.52,
        "涨跌幅": -2.06
    },
    {
        "代码": 600114,
        "l2name": "通用机械II",
        "名称": "东睦股份",
        "总净流入占比_5日总和": 67.74,
        "PotScore": 0.37,
        "收盘价": 30.12,
        "涨跌幅": 3.22
    },
    {
        "代码": 3031,
        "l2name": "通信设备II",
        "名称": "中瓷电子",
        "总净流入占比_5日总和": 160.31,
        "PotScore": 3.93,
        "收盘价": 71.84,
        "涨跌幅": 10.0
    },
    {
        "代码": 70,
        "l2name": "通信设备II",
        "名称": "特发信息",
        "总净流入占比_5日总和": 51.72,
        "PotScore": null,
        "收盘价": 14.85,
        "涨跌幅": 10.0
    },
    {
        "代码": 688027,
        "l2name": "通信设备II",
        "名称": "国盾量子",
        "总净流入占比_5日总和": 39.53,
        "PotScore": -0.31,
        "收盘价": 489.11,
        "涨跌幅": -1.59
    },
    {
        "代码": 603386,
        "l2name": "元件II",
        "名称": "骏亚科技",
        "总净流入占比_5日总和": 62.70999999999999,
        "PotScore": 1.46,
        "收盘价": 18.14,
        "涨跌幅": -9.98
    },
    {
        "代码": 2913,
        "l2name": "元件II",
        "名称": "奥士康",
        "总净流入占比_5日总和": 23.46,
        "PotScore": 0.55,
        "收盘价": 43.19,
        "涨跌幅": 3.95
    },
    {
        "代码": 823,
        "l2name": "元件II",
        "名称": "超声电子",
        "总净流入占比_5日总和": 23.01,
        "PotScore": 1.05,
        "收盘价": 15.88,
        "涨跌幅": -0.5
    }
]