[
    {
        "基金简称": "恒生互联",
        "份额增长%": 972.33
    },
    {
        "基金简称": "券商ETF",
        "份额增长%": 258.44
    },
    {
        "基金简称": "医疗ETF",
        "份额增长%": 4646.5
    },
    {
        "基金简称": "酒ETF",
        "份额增长%": 1166.95
    },
    {
        "基金简称": "医疗器械ETF永赢",
        "份额增长%": 5483.38
    },
    {
        "基金简称": "医药ETF",
        "份额增长%": 1463.22
    },
    {
        "基金简称": "消费ETF汇添富",
        "份额增长%": 1499.26
    },
    {
        "基金简称": "疫苗ETF国泰",
        "份额增长%": 6.21
    },
    {
        "基金简称": "恒生医疗",
        "份额增长%": 5472.26
    },
    {
        "基金简称": "电子ETF",
        "份额增长%": -71.27
    },
    {
        "基金简称": "芯片ETF",
        "份额增长%": -10.69
    },
    {
        "基金简称": "畜牧养殖",
        "份额增长%": 1892.11
    },
    {
        "基金简称": "银行ETF",
        "份额增长%": 59.84
    },
    {
        "基金简称": "疫苗ETF",
        "份额增长%": -80.39
    },
    {
        "基金简称": "软件ETF",
        "份额增长%": 1078.27
    },
    {
        "基金简称": "50ETF",
        "份额增长%": 40.87
    },
    {
        "基金简称": "光伏ETF",
        "份额增长%": 13.2
    },
    {
        "基金简称": "300ETF",
        "份额增长%": 386.1
    },
    {
        "基金简称": "恒生中国",
        "份额增长%": -52.22
    },
    {
        "基金简称": "中药",
        "份额增长%": -76.13
    },
    {
        "基金简称": "煤炭ETF",
        "份额增长%": 1380.7
    },
    {
        "基金简称": "军工ETF",
        "份额增长%": -11.39
    },
    {
        "基金简称": "新能源车ETF东财",
        "份额增长%": 16.55
    },
    {
        "基金简称": "机器人ETF天弘",
        "份额增长%": 4121.3
    },
    {
        "基金简称": "科创50",
        "份额增长%": 468.94
    },
    {
        "基金简称": "交通运输ETF华夏",
        "份额增长%": -75.85
    },
    {
        "基金简称": "化工ETF",
        "份额增长%": 458.96
    },
    {
        "基金简称": "智能汽车",
        "份额增长%": 31.15
    },
    {
        "基金简称": "科创创业ETF易方达",
        "份额增长%": 144.27
    },
    {
        "基金简称": "800ETF",
        "份额增长%": 105.26
    },
    {
        "基金简称": "金融ETF",
        "份额增长%": -23.14
    },
    {
        "基金简称": "综指ETF",
        "份额增长%": 1326.65
    },
    {
        "基金简称": "30年国债",
        "份额增长%": 12221.74
    },
    {
        "基金简称": "通信ETF",
        "份额增长%": 420.54
    },
    {
        "基金简称": "传媒ETF",
        "份额增长%": 83.14
    },
    {
        "基金简称": "创业板ETF易方达",
        "份额增长%": 175.81
    },
    {
        "基金简称": "道琼斯",
        "份额增长%": 727.23
    },
    {
        "基金简称": "央企分红",
        "份额增长%": -91.9
    },
    {
        "基金简称": "钢铁ETF",
        "份额增长%": 765.03
    },
    {
        "基金简称": "游戏ETF",
        "份额增长%": 174.71
    },
    {
        "基金简称": "创业板50ETF华安",
        "份额增长%": 48.24
    },
    {
        "基金简称": "上证ETF",
        "份额增长%": 163.12
    },
    {
        "基金简称": "电力ETF",
        "份额增长%": 950.2
    },
    {
        "基金简称": "中证500",
        "份额增长%": 113.68
    },
    {
        "基金简称": "HK创新药",
        "份额增长%": 9620.08
    },
    {
        "基金简称": "半导体",
        "份额增长%": 27.08
    },
    {
        "基金简称": "中证红利",
        "份额增长%": 1360.2
    },
    {
        "基金简称": "东证ETF",
        "份额增长%": 1991.76
    },
    {
        "基金简称": "纳指生物",
        "份额增长%": 392.5
    },
    {
        "基金简称": "日经ETF",
        "份额增长%": 1396.83
    },
    {
        "基金简称": "央创ETF",
        "份额增长%": -51.56
    },
    {
        "基金简称": "地产ETF",
        "份额增长%": 60.41
    },
    {
        "基金简称": "AI智能",
        "份额增长%": 297.71
    },
    {
        "基金简称": "云计算",
        "份额增长%": 289.91
    },
    {
        "基金简称": "工业母机ETF国泰",
        "份额增长%": 62.33
    },
    {
        "基金简称": "有色ETF汇添富",
        "份额增长%": 151.22
    },
    {
        "基金简称": "红利低波",
        "份额增长%": 21489.17
    },
    {
        "基金简称": "标普500",
        "份额增长%": 343.57
    },
    {
        "基金简称": "纳指ETF",
        "份额增长%": 406.52
    },
    {
        "基金简称": "黄金ETF",
        "份额增长%": 344.26
    },
    {
        "基金简称": "资源ETF",
        "份额增长%": 5.38
    }
]