[
    {
        "代码": 600488,
        "l2name": "化学制药II",
        "名称": "津药药业",
        "总净流入占比_5日总和": 130.82,
        "PotScore": 1.87,
        "收盘价": 7.08,
        "涨跌幅": -3.8
    },
    {
        "代码": 603538,
        "l2name": "化学制药II",
        "名称": "美诺华",
        "总净流入占比_5日总和": 119.11,
        "PotScore": 2.52,
        "收盘价": 45.5,
        "涨跌幅": 5.23
    },
    {
        "代码": 919,
        "l2name": "化学制药II",
        "名称": "金陵药业",
        "总净流入占比_5日总和": 70.87,
        "PotScore": 2.22,
        "收盘价": 8.58,
        "涨跌幅": -3.7
    },
    {
        "代码": 586,
        "l2name": "通信设备II",
        "名称": "汇源通信",
        "总净流入占比_5日总和": 264.31,
        "PotScore": 2.83,
        "收盘价": 25.12,
        "涨跌幅": 9.98
    },
    {
        "代码": 2491,
        "l2name": "通信设备II",
        "名称": "通鼎互联",
        "总净流入占比_5日总和": 76.56,
        "PotScore": 1.93,
        "收盘价": 16.14,
        "涨跌幅": 6.18
    },
    {
        "代码": 603042,
        "l2name": "通信设备II",
        "名称": "华脉科技",
        "总净流入占比_5日总和": 75.35,
        "PotScore": 1.51,
        "收盘价": 23.34,
        "涨跌幅": 4.57
    },
    {
        "代码": 720,
        "l2name": "电网设备II",
        "名称": "新能泰山",
        "总净流入占比_5日总和": 46.61,
        "PotScore": 1.6,
        "收盘价": 6.03,
        "涨跌幅": -10.0
    },
    {
        "代码": 2980,
        "l2name": "电网设备II",
        "名称": "华盛昌",
        "总净流入占比_5日总和": 42.55,
        "PotScore": 2.0,
        "收盘价": 55.68,
        "涨跌幅": 5.33
    },
    {
        "代码": 301291,
        "l2name": "电网设备II",
        "名称": "明阳电气",
        "总净流入占比_5日总和": 38.83,
        "PotScore": 0.17,
        "收盘价": 52.88,
        "涨跌幅": -0.38
    }
]