[
    {
        "l2name": "半导体II",
        "PotScore": 386.72,
        "主力净流入-净占比": -539.98
    },
    {
        "l2name": "元件II",
        "PotScore": 146.7,
        "主力净流入-净占比": -55.62
    },
    {
        "l2name": "电子化学品II",
        "PotScore": 117.4,
        "主力净流入-净占比": 5.480000000000006
    },
    {
        "l2name": "光学光电子II",
        "PotScore": 116.86,
        "主力净流入-净占比": -225.25
    },
    {
        "l2name": "通用机械II",
        "PotScore": 102.15,
        "主力净流入-净占比": -1633.05
    },
    {
        "l2name": "自动化设备II",
        "PotScore": 75.2,
        "主力净流入-净占比": -375.14
    },
    {
        "l2name": "化学制品II",
        "PotScore": 68.34,
        "主力净流入-净占比": -1163.2
    },
    {
        "l2name": "电子制造II",
        "PotScore": 67.18,
        "主力净流入-净占比": -879.73
    },
    {
        "l2name": "其他电子II",
        "PotScore": 56.35,
        "主力净流入-净占比": -423.5
    },
    {
        "l2name": "塑料II",
        "PotScore": 48.33,
        "主力净流入-净占比": -731.95
    }
]