[
    {
        "l2name": "通用机械II",
        "PotScore": 137.21,
        "主力净流入-净占比": -2080.34
    },
    {
        "l2name": "通信设备II",
        "PotScore": 126.77,
        "主力净流入-净占比": -774.74
    },
    {
        "l2name": "军工电子II",
        "PotScore": 95.23,
        "主力净流入-净占比": -363.03
    },
    {
        "l2name": "汽车零部件II",
        "PotScore": 89.39,
        "主力净流入-净占比": -2715.19
    },
    {
        "l2name": "一般零售II",
        "PotScore": 79.66,
        "主力净流入-净占比": -1087.12
    },
    {
        "l2name": "电网设备II",
        "PotScore": 60.97,
        "主力净流入-净占比": -1206.37
    },
    {
        "l2name": "元件II",
        "PotScore": 48.51,
        "主力净流入-净占比": -422.21
    },
    {
        "l2name": "电子制造II",
        "PotScore": 47.84,
        "主力净流入-净占比": -874.1
    },
    {
        "l2name": "稀有金属II",
        "PotScore": 46.85,
        "主力净流入-净占比": -88.69999999999999
    },
    {
        "l2name": "包装印刷II",
        "PotScore": 46.58,
        "主力净流入-净占比": -212.44
    }
]