[
    {
        "代码": 2207,
        "l2name": "油服工程II",
        "名称": "准油股份",
        "总净流入占比_5日总和": 194.74,
        "PotScore": 0.9,
        "收盘价": 12.42,
        "涨跌幅": 10.01
    },
    {
        "代码": 603619,
        "l2name": "油服工程II",
        "名称": "中曼石油",
        "总净流入占比_5日总和": 86.25999999999999,
        "PotScore": 0.89,
        "收盘价": 39.99,
        "涨跌幅": 10.01
    },
    {
        "代码": 2554,
        "l2name": "油服工程II",
        "名称": "惠博普",
        "总净流入占比_5日总和": 78.64999999999999,
        "PotScore": null,
        "收盘价": 4.66,
        "涨跌幅": 9.91
    },
    {
        "代码": 2428,
        "l2name": "稀有金属II",
        "名称": "云南锗业",
        "总净流入占比_5日总和": 123.7,
        "PotScore": 0.91,
        "收盘价": 45.68,
        "涨跌幅": -5.35
    },
    {
        "代码": 2182,
        "l2name": "稀有金属II",
        "名称": "宝武镁业",
        "总净流入占比_5日总和": 74.21000000000001,
        "PotScore": 0.78,
        "收盘价": 22.85,
        "涨跌幅": 4.86
    },
    {
        "代码": 2978,
        "l2name": "稀有金属II",
        "名称": "安宁股份",
        "总净流入占比_5日总和": 55.38,
        "PotScore": 0.36,
        "收盘价": 42.67,
        "涨跌幅": 0.23
    },
    {
        "代码": 601528,
        "l2name": "农商行II",
        "名称": "瑞丰银行",
        "总净流入占比_5日总和": 69.21,
        "PotScore": -0.13,
        "收盘价": 5.46,
        "涨跌幅": 0.0
    },
    {
        "代码": 600908,
        "l2name": "农商行II",
        "名称": "无锡银行",
        "总净流入占比_5日总和": 46.33,
        "PotScore": -0.03,
        "收盘价": 5.92,
        "涨跌幅": 0.85
    },
    {
        "代码": 603323,
        "l2name": "农商行II",
        "名称": "苏农银行",
        "总净流入占比_5日总和": 38.91,
        "PotScore": -0.1,
        "收盘价": 5.04,
        "涨跌幅": -0.2
    }
]