[
    {
        "代码": 688084,
        "l2name": "军工电子II",
        "名称": "晶品特装",
        "总净流入占比_5日总和": 46.51,
        "PotScore": 0.28,
        "收盘价": 96.01,
        "涨跌幅": 0.59
    },
    {
        "代码": 688053,
        "l2name": "军工电子II",
        "名称": "ST思科瑞",
        "总净流入占比_5日总和": 38.06,
        "PotScore": null,
        "收盘价": 51.08,
        "涨跌幅": -6.6
    },
    {
        "代码": 688636,
        "l2name": "军工电子II",
        "名称": "智明达",
        "总净流入占比_5日总和": 37.08000000000001,
        "PotScore": 1.03,
        "收盘价": 55.8,
        "涨跌幅": -7.0
    },
    {
        "代码": 3007,
        "l2name": "软件开发II",
        "名称": "直真科技",
        "总净流入占比_5日总和": 196.05,
        "PotScore": 1.13,
        "收盘价": 54.34,
        "涨跌幅": 10.0
    },
    {
        "代码": 301378,
        "l2name": "软件开发II",
        "名称": "通达海",
        "总净流入占比_5日总和": 106.93,
        "PotScore": 1.87,
        "收盘价": 45.49,
        "涨跌幅": 19.99
    },
    {
        "代码": 503,
        "l2name": "软件开发II",
        "名称": "国新健康",
        "总净流入占比_5日总和": 102.29,
        "PotScore": 0.96,
        "收盘价": 11.33,
        "涨跌幅": -2.41
    },
    {
        "代码": 2112,
        "l2name": "电网设备II",
        "名称": "三变科技",
        "总净流入占比_5日总和": 96.62,
        "PotScore": 1.02,
        "收盘价": 17.48,
        "涨跌幅": 10.01
    },
    {
        "代码": 688248,
        "l2name": "电网设备II",
        "名称": "南网科技",
        "总净流入占比_5日总和": 81.44,
        "PotScore": 0.36,
        "收盘价": 54.58,
        "涨跌幅": -0.4
    },
    {
        "代码": 601179,
        "l2name": "电网设备II",
        "名称": "中国西电",
        "总净流入占比_5日总和": 46.25999999999999,
        "PotScore": 0.95,
        "收盘价": 12.4,
        "涨跌幅": 8.87
    }
]